agensight/__init__.py
agensight/_version.py
agensight/config_template.py
agensight/_server/__init__.py
agensight/_server/app.py
agensight/_server/data_source.py
agensight/_server/migration_util.py
agensight/_server/models.py
agensight/_server/run.py
agensight/_server/routes/__init__.py
agensight/_server/routes/config.py
agensight/_server/routes/metrics.py
agensight/_server/routes/prompt.py
agensight/_server/routes/trace.py
agensight/_server/utils/__init__.py
agensight/_server/utils/config_utils.py
agensight/_server/utils/file_ops.py
agensight/_ui/node_modules/flatted/python/flatted.py
agensight/_ui/out/404.html
agensight/_ui/out/dashboard.html
agensight/_ui/out/dashboard.txt
agensight/_ui/out/favicon.ico
agensight/_ui/out/file.svg
agensight/_ui/out/globe.svg
agensight/_ui/out/index.html
agensight/_ui/out/index.txt
agensight/_ui/out/next.svg
agensight/_ui/out/pype-logo.png
agensight/_ui/out/session-replay.html
agensight/_ui/out/session-replay.txt
agensight/_ui/out/session.html
agensight/_ui/out/session.txt
agensight/_ui/out/sessions.html
agensight/_ui/out/sessions.txt
agensight/_ui/out/trace.html
agensight/_ui/out/trace.txt
agensight/_ui/out/traces.html
agensight/_ui/out/traces.txt
agensight/_ui/out/vercel.svg
agensight/_ui/out/window.svg
agensight/_ui/out/_next/static/7zM_Xks_eIXlJ6FrnACED/_buildManifest.js
agensight/_ui/out/_next/static/7zM_Xks_eIXlJ6FrnACED/_ssgManifest.js
agensight/_ui/out/_next/static/chunks/0e5ce63c-4b17bc6a0c8fba66.js
agensight/_ui/out/_next/static/chunks/116-f8a20243fd012e42.js
agensight/_ui/out/_next/static/chunks/126-99084218984fa233.js
agensight/_ui/out/_next/static/chunks/328-89dee8efe331d11c.js
agensight/_ui/out/_next/static/chunks/348-f604332615007508.js
agensight/_ui/out/_next/static/chunks/423-317082e06a58f58a.js
agensight/_ui/out/_next/static/chunks/4bd1b696-00aa43bf93bc9168.js
agensight/_ui/out/_next/static/chunks/522-cce7b631916e0f28.js
agensight/_ui/out/_next/static/chunks/525-2411d0d5cdbd1ab5.js
agensight-0.6.3.dist-info/METADATA
agensight-0.6.3.dist-info/WHEEL
agensight-0.6.3.dist-info/entry_points.txt
agensight-0.6.3.dist-info/top_level.txt
agensight-0.6.3.dist-info/RECORD
